pyautoupdate/__init__.py
pyautoupdate/_file_glob.py
pyautoupdate/exceptions.py
pyautoupdate/launcher.py
pyautoupdate/ntcommonpath.py
pyautoupdate/posixcommonpath.py
pyautoupdate-1.0.0.post1.dist-info/DESCRIPTION.rst
pyautoupdate-1.0.0.post1.dist-info/METADATA
pyautoupdate-1.0.0.post1.dist-info/RECORD
pyautoupdate-1.0.0.post1.dist-info/WHEEL
pyautoupdate-1.0.0.post1.dist-info/metadata.json
pyautoupdate-1.0.0.post1.dist-info/top_level.txt
test/__init__.py
test/pytest_makevers.py
test/pytest_skipif.py
test/test_check_update.py
test/test_get_new.py
test/test_mk_dirs.py
test/test_no_update.py
test/test_parameters.py
test/test_replace_files.py
test/test_rm_dirs.py
test/test_run.py
test/test_update.py
