Metadata-Version: 1.1
Name: pyautoupdate
Version: 1.0.0.post1
Summary: Auto-update API for Python programs
Home-page: https://github.com/rlee287/pyautoupdate
Author: Ryan Lee
Author-email: rndprogrammer@yahoo.com
License: LGPL 2.1
Platform: UNKNOWN
Classifier: Intended Audience :: Developers
Classifier: Development Status :: 4 - Beta
Classifier: License :: OSI Approved :: GNU Lesser General Public License v2 or later (LGPLv2+)
Classifier: Programming Language :: Python
Classifier: Programming Language :: Python :: 2.6
Classifier: Programming Language :: Python :: 2.7
Classifier: Programming Language :: Python :: 3
Classifier: Programming Language :: Python :: 3.3
Classifier: Programming Language :: Python :: 3.4
Classifier: Programming Language :: Python :: 3.5
Classifier: Programming Language :: Python :: Implementation :: CPython
Classifier: Programming Language :: Python :: Implementation :: PyPy
